sqlalchemy_batch_inserts
