Metadata-Version: 2.1
Name: sqlalchemy-batch-inserts
Version: 0.0.3
Summary: Batch inserts for SQLAlchemy on PostgreSQL with psycopg2
Home-page: https://github.com/benchling/sqlalchemy_batch_inserts
Author: Vineet Gopal
Author-email: vineet@benchling.com
License: UNKNOWN
Platform: UNKNOWN
Classifier: Programming Language :: Python :: 2.7
Classifier: Programming Language :: Python :: 3
Classifier: License :: OSI Approved :: MIT License
Classifier: Operating System :: OS Independent
